wiki/__about__.py
wiki/__init__.py
wiki/admin.py
wiki/apps.py
wiki/checks.py
wiki/decorators.py
wiki/forms.py
wiki/forms_account_handling.py
wiki/managers.py
wiki/sites.py
wiki/urls.py
wiki/conf/__init__.py
wiki/conf/settings.py
wiki/core/__init__.py
wiki/core/diff.py
wiki/core/exceptions.py
wiki/core/http.py
wiki/core/paginator.py
wiki/core/permissions.py
wiki/core/utils.py
wiki/core/markdown/__init__.py
wiki/core/markdown/mdx/__init__.py
wiki/core/markdown/mdx/codehilite.py
wiki/core/markdown/mdx/previewlinks.py
wiki/core/markdown/mdx/responsivetable.py
wiki/core/plugins/__init__.py
wiki/core/plugins/base.py
wiki/core/plugins/loader.py
wiki/core/plugins/registry.py
wiki/editors/__init__.py
wiki/editors/base.py
wiki/editors/markitup.py
wiki/locale/ca/LC_MESSAGES/django.mo
wiki/locale/cs/LC_MESSAGES/django.mo
wiki/locale/da/LC_MESSAGES/django.mo
wiki/locale/de/LC_MESSAGES/django.mo
wiki/locale/el/LC_MESSAGES/django.mo
wiki/locale/en/LC_MESSAGES/django.po
wiki/locale/es/LC_MESSAGES/django.mo
wiki/locale/fi/LC_MESSAGES/django.mo
wiki/locale/fr/LC_MESSAGES/django.mo
wiki/locale/hu/LC_MESSAGES/django.mo
wiki/locale/it/LC_MESSAGES/django.mo
wiki/locale/ja/LC_MESSAGES/django.mo
wiki/locale/ko_KR/LC_MESSAGES/django.mo
wiki/locale/nb_NO/LC_MESSAGES/django.mo
wiki/locale/nl/LC_MESSAGES/django.mo
wiki/locale/pl_PL/LC_MESSAGES/django.mo
wiki/locale/pt/LC_MESSAGES/django.mo
wiki/locale/pt_BR/LC_MESSAGES/django.mo
wiki/locale/ro/LC_MESSAGES/django.mo
wiki/locale/ru/LC_MESSAGES/django.mo
wiki/locale/sk/LC_MESSAGES/django.mo
wiki/locale/sv/LC_MESSAGES/django.mo
wiki/locale/tr_TR/LC_MESSAGES/django.mo
wiki/locale/zh_CN/LC_MESSAGES/django.mo
wiki/locale/zh_TW/LC_MESSAGES/django.mo
wiki/migrations/0001_initial.py
wiki/migrations/0002_urlpath_moved_to.py
wiki/migrations/0003_mptt_upgrade.py
wiki/migrations/__init__.py
wiki/models/__init__.py
wiki/models/article.py
wiki/models/pluginbase.py
wiki/models/urlpath.py
wiki/plugins/__init__.py
wiki/plugins/attachments/__init__.py
wiki-0.12.1.dist-info/METADATA
wiki-0.12.1.dist-info/WHEEL
wiki-0.12.1.dist-info/licenses/COPYING
wiki-0.12.1.dist-info/RECORD
