Metadata-Version: 2.4
Name: wiki
Version: 0.12.1
Summary: A wiki system written for the Django framework.
Project-URL: Homepage, http://www.django-wiki.org
Project-URL: Documentation, https://django-wiki.readthedocs.io/en/latest/
Project-URL: Tracker, https://github.com/django-wiki/django-wiki/issues
Project-URL: Source, https://github.com/django-wiki/django-wiki
Author-email: Benjamin Bach <benjamin@overtag.dk>
Maintainer-email: Oscar Cortez <om.cortez.2010@gmail.com>
License-Expression: GPL-3.0
License-File: COPYING
Keywords: django,markdown,wiki
Classifier: Development Status :: 5 - Production/Stable
Classifier: Environment :: Web Environment
Classifier: Framework :: Django
Classifier: Intended Audience :: Developers
Classifier: License :: OSI Approved :: GNU General Public License v3 (GPLv3)
Classifier: Operating System :: OS Independent
Classifier: Programming Language :: Python
Classifier: Programming Language :: Python :: 3 :: Only
Classifier: Programming Language :: Python :: 3.9
Classifier: Programming Language :: Python :: 3.10
Classifier: Programming Language :: Python :: 3.11
Classifier: Programming Language :: Python :: 3.12
Classifier: Programming Language :: Python :: 3.13
Classifier: Programming Language :: Python :: Implementation :: CPython
Classifier: Programming Language :: Python :: Implementation :: PyPy
Classifier: Topic :: Internet :: WWW/HTTP :: Dynamic Content
Classifier: Topic :: Internet :: WWW/HTTP :: Dynamic Content :: Wiki
Classifier: Topic :: Software Development
Classifier: Topic :: Software Development :: Libraries :: Application Frameworks
Requires-Python: >=3.9
Requires-Dist: bleach[css]<7,>=6
Requires-Dist: django-mptt<0.17,>=0.13
Requires-Dist: django-nyt<1.5,>=1.4.2
Requires-Dist: django-sekizai>=0.10
Requires-Dist: django<5.3,>=4.0
Requires-Dist: markdown<3.10,>=3.4
Requires-Dist: pillow
Requires-Dist: pymdown-extensions<10.6,>=10.5
Requires-Dist: sorl-thumbnail<13,>=12.8
Provides-Extra: docs
Requires-Dist: sphinx-rtd-theme==2.0.0; extra == 'docs'
Requires-Dist: sphinx<8,>=6; extra == 'docs'
